Metadata-Version: 1.0
Name: epprintname
Version: 0.0.1
Summary: This is test package to learn distribution on open source
Home-page: UNKNOWN
Author: EP
Author-email: UNKNOWN
License: UNKNOWN
Platform: UNKNOWN
